aio/functional/__init__.py
aio/functional/decorators.py
aio/functional/py.typed
aio.functional-0.0.10.dist-info/METADATA
aio.functional-0.0.10.dist-info/WHEEL
aio.functional-0.0.10.dist-info/namespace_packages.txt
aio.functional-0.0.10.dist-info/top_level.txt
aio.functional-0.0.10.dist-info/RECORD
