Metadata-Version: 2.1
Name: aio.functional
Version: 0.0.10
Summary: A collection of functional utils for asyncio
Home-page: https://github.com/envoyproxy/pytooling/tree/main/aio.functional
Author: Ryan Northey
Author-email: ryan@synca.io
Maintainer: Ryan Northey
Maintainer-email: ryan@synca.io
License: Apache Software License 2.0
Platform: UNKNOWN
